adapters/__init__.py
adapters/abstract_adapters/__init__.py
adapters/abstract_adapters/api_key_adapter_mixin.py
adapters/abstract_adapters/base_adapter.py
adapters/abstract_adapters/openai_sdk_chat_adapter.py
adapters/abstract_adapters/provider_adapter_mixin.py
adapters/abstract_adapters/sdk_chat_adapter.py
adapters/adapter_factory.py
adapters/client_cache.py
adapters/constants.py
adapters/custom_sdk_chat_provider_adapter.py
adapters/general_utils.py
adapters/provider_adapters/__init__.py
adapters/provider_adapters/ai21_sdk_chat_provider_adapter.py
adapters/provider_adapters/anthropic_sdk_chat_provider_adapter.py
adapters/provider_adapters/azure_sdk_chat_provider_adapter.py
adapters/provider_adapters/cerebras_sdk_chat_provider_adapter.py
adapters/provider_adapters/cohere_sdk_chat_provider_adapter.py
adapters/provider_adapters/databricks_sdk_chat_provider_adapter.py
adapters/provider_adapters/deepinfra_sdk_chat_provider_adapter.py
adapters/provider_adapters/fireworks_sdk_chat_provider_adapter.py
adapters/provider_adapters/gemini_sdk_chat_provider_adapter.py
adapters/provider_adapters/groq_sdk_chat_provider_adapter.py
adapters/provider_adapters/lepton_sdk_chat_provider_adapter.py
adapters/provider_adapters/moonshot_sdk_chat_provider_adapter.py
adapters/provider_adapters/octoai_sdk_chat_provider_adapter.py
adapters/provider_adapters/openai_sdk_chat_provider_adapter.py
adapters/provider_adapters/openrouter_sdk_chat_provider_adapter.py
adapters/provider_adapters/perplexity_sdk_chat_provider_adapter.py
adapters/provider_adapters/together_sdk_chat_provider_adapter.py
adapters/provider_adapters/vertex_sdk_chat_provider_adapter.py
adapters/types.py
martian_adapters_wyzerstudio-7.0.0a2.dist-info/LICENSE
martian_adapters_wyzerstudio-7.0.0a2.dist-info/METADATA
martian_adapters_wyzerstudio-7.0.0a2.dist-info/WHEEL
martian_adapters_wyzerstudio-7.0.0a2.dist-info/RECORD
