Metadata-Version: 2.1
Name: martian-adapters-wyzerstudio
Version: 7.0.0a2
Summary: Adapters as API gateways to Different LLM Models
Author: Martian team
Author-email: team@withmartian.com
Requires-Python: >=3.11,<4.0
Classifier: Programming Language :: Python :: 3
Classifier: Programming Language :: Python :: 3.11
Classifier: Programming Language :: Python :: 3.12
Classifier: Programming Language :: Python :: 3.13
Requires-Dist: anthropic (>=0.39.0,<0.40.0)
Requires-Dist: brotli (>=1.1.0,<2.0.0)
Requires-Dist: cohere (>=5.11.3,<6.0.0)
Requires-Dist: google-generativeai (>=0.8.3,<0.9.0)
Requires-Dist: openai (>=1.54.1,<2.0.0)
Requires-Dist: pydantic (>=2.9.2,<3.0.0)
